{
  "metadata": {
    "title": "Studies on Iraqi population of Drosophila melanogaster inhabiting Tuwaitha area.",
    "upload_type": "publication",
    "description": "uploaded by Plazi from Taxodros",
    "access_right": "open",
    "journal_pages": "295-304",
    "journal_title": "J. Biol. Sci. Res., Baghdad",
    "journal_volume": "16",
    "publication_type": "article",
    "publication_date": "1985-07-31",
    "keywords": [
      "Biodiversity",
      "Taxonomy",
      "Animalia",
      "Arthropoda",
      "Insecta",
      "Diptera",
      "Drosophilidae",
      "flies",
      "fruit flies",
      "terrestrial"
    ],
    "license": "cc-by",
    "creators": [
      {
        "name": "Al-Hakkak, Z.S."
      },
      {
        "name": "Ahmed, M.S.H."
      },
      {
        "name": "Ali, S.R."
      },
      {
        "name": "Lamooza, S.B."
      },
      {
        "name": "Al-Maliky, S.K."
      },
      {
        "name": "and Kadhum, A.-R.A."
      }
    ],
    "communities": [
      {
        "identifier": "biosyslit"
      }
    ]
  }
}
